fcs_core_model_engine/__init__.py
fcs_core_model_engine/fcscore.pyi
fcs_core_model_engine/fcscore.so
fcs_core_model_engine/fcscore_core.pyi
fcs_core_model_engine/fcscore_geometry.pyi
fcs_core_model_engine/fcscore_mesh.pyi
fcs_core_model_engine/fcscore_model.pyi
fcs_core_model_engine/fcslogger.py
fcs_core_model_engine/fcsmodelsession.py
fcs_core_model_engine/fcsoptions.py
fcs_core_model_engine/fcsservice.py
fcs_core_model_engine/geometrybuilder.py
fcs_core_model_engine/libBlockFix.so
fcs_core_model_engine/libFCS.ModelEngine.Core.so
fcs_core_model_engine/libFCS.ModelEngine.Geometry.so
fcs_core_model_engine/libFCS.ModelEngine.Mesh.so
fcs_core_model_engine/libFCS.ModelEngine.Model.so
fcs_core_model_engine/libGEOM.so
fcs_core_model_engine/libGEOMAlgo.so
fcs_core_model_engine/libGEOMImpl.so
fcs_core_model_engine/libGEOMUtils.so
fcs_core_model_engine/libSALOMEBasics.so
fcs_core_model_engine/libSALOMELocalTrace.so
fcs_core_model_engine/libSTEPPlugin.so
fcs_core_model_engine/libShHealOper.so
fcs_core_model_engine/libSketcher.so
fcs_core_model_engine/libTKBO.so
fcs_core_model_engine/libTKBO.so.7
fcs_core_model_engine/libTKBO.so.7.4.0
fcs_core_model_engine/libTKBRep.so
fcs_core_model_engine/libTKBRep.so.7
fcs_core_model_engine/libTKBRep.so.7.4.0
fcs_core_model_engine/libTKBin.so
fcs_core_model_engine/libTKBin.so.7
fcs_core_model_engine/libTKBin.so.7.4.0
fcs_core_model_engine/libTKBinL.so
fcs_core_model_engine/libTKBinL.so.7
fcs_core_model_engine/libTKBinL.so.7.4.0
fcs_core_model_engine/libTKBinTObj.so
fcs_core_model_engine/libTKBinTObj.so.7
fcs_core_model_engine/libTKBinTObj.so.7.4.0
fcs_core_model_engine/libTKBinXCAF.so
fcs_core_model_engine/libTKBinXCAF.so.7
fcs_core_model_engine/libTKBinXCAF.so.7.4.0
fcs_core_model_engine/libTKBool.so
fcs_core_model_engine/libTKBool.so.7
fcs_core_model_engine/libTKBool.so.7.4.0
fcs_core_model_engine/libTKCAF.so
fcs_core_model_engine/libTKCAF.so.7
fcs_core_model_engine/libTKCAF.so.7.4.0
fcs_core_model_engine/libTKCDF.so
fcs_core_model_engine-0.42.4.dist-info/LICENSE
fcs_core_model_engine-0.42.4.dist-info/METADATA
fcs_core_model_engine-0.42.4.dist-info/WHEEL
fcs_core_model_engine-0.42.4.dist-info/top_level.txt
fcs_core_model_engine-0.42.4.dist-info/RECORD
