Metadata-Version: 2.1
Name: fcs-core-model-engine
Version: 0.42.4
Summary: Python bound methods to FCS.Core.ModelEngine libraries.
Home-page: https://github.com/Femsolve-Engineering/FCS.Core.ModelEngine.PyAPI
Author: Tamas Balogh
Author-email: info@femsolve.com
License: UNKNOWN
Platform: UNKNOWN
Classifier: Programming Language :: Python :: 3.11
Classifier: License :: OSI Approved :: MIT License
Classifier: Operating System :: Microsoft :: Windows
Classifier: Operating System :: POSIX :: Linux
Requires-Python: >=3.11, <3.12
License-File: LICENSE
Requires-Dist: gmsh (==4.11.1)
Provides-Extra: dev
Requires-Dist: pytest (>=7.0) ; extra == 'dev'
Requires-Dist: twine (>=4.0.2) ; extra == 'dev'
